deps/__init__.py
deps/__main__.py
deps/config.py
deps/storage.py
deps/version.py
deps/cli/__init__.py
deps/cli/main.py
deps/environment_configuration/__init__.py
deps/environment_configuration/view.py
deps/pipenv/__init__.py
deps/pipenv/resolver.py
deps/pipenv/view.py
scripts/__init__.py
tests/__init__.py
tests/conftest.py
tests/test_pass.py
deps-0.2.3.dist-info/LICENSE.md
deps-0.2.3.dist-info/METADATA
deps-0.2.3.dist-info/WHEEL
deps-0.2.3.dist-info/entry_points.txt
deps-0.2.3.dist-info/top_level.txt
deps-0.2.3.dist-info/RECORD
