Metadata-Version: 2.1
Name: deps
Version: 0.2.3
Summary: A terminal UI dashboard to view python dependencies across Github repositories.
Download-URL: https://pypi.org/project/deps/
Author: Kyle Harrison
Author-email: kyle.harrison.dev@gmail.com
License: MIT
Project-URL: Funding, https://ko-fi.com/apoclyps
Project-URL: Say Thanks!, https://twitter.com/apoclyps
Project-URL: Source, https://github.com/apoclyps/deps
Project-URL: Tracker, https://github.com/apoclyps/deps/issues
Keywords: Deps
Classifier: Development Status :: 3 - Alpha
Classifier: Environment :: Console
Classifier: Intended Audience :: Developers
Classifier: License :: OSI Approved :: MIT License
Classifier: Natural Language :: English
Classifier: Operating System :: MacOS
Classifier: Operating System :: Microsoft :: Windows :: Windows 10
Classifier: Operating System :: Unix
Classifier: Programming Language :: Python :: 3.10
Classifier: Programming Language :: Python :: 3.11
Classifier: Topic :: Terminals
License-File: LICENSE.md
